{
  "selected_features": [
    "RSI",
    "MACD",
    "MACD_signal",
    "MACD_hist",
    "BB_Width",
    "Dist_SMA50",
    "Dist_SMA200",
    "Return_1d",
    "Return_5d",
    "OBV_Momentum",
    "Volume_Ratio",
    "VWAP_Dev",
    "ATR_Pct",
    "BB_PctB",
    "Vol_Ratio"
  ],
  "all_features": [
    "RSI",
    "MACD",
    "MACD_signal",
    "MACD_hist",
    "BB_Width",
    "Dist_SMA50",
    "Dist_SMA200",
    "Return_1d",
    "Return_5d",
    "OBV_Momentum",
    "Volume_Ratio",
    "VWAP_Dev",
    "ATR_Pct",
    "BB_PctB",
    "Vol_Ratio"
  ],
  "training_date": "2026-03-01T20:23:10.098690",
  "training_samples": 1876579,
  "xgboost_version": "2.0.3",
  "prediction_stats": {
    "mean": 0.0007153668557293713,
    "std": 0.0024224738590419292,
    "min": -0.12814532220363617,
    "max": 0.28432929515838623,
    "expected_range": [
      -0.1,
      0.1
    ]
  },
  "cv_metrics": {
    "avg_rmse": 0.0196674591591754,
    "avg_dir_accuracy": 0.5215949456937041,
    "avg_spearman": 0.024046605753867183
  }
}